{
  "main": {
    "id": "f12781570a485425",
    "type": "split",
    "children": [
      {
        "id": "35d1e8f72a7a37c3",
        "type": "tabs",
        "children": [
          {
            "id": "f659e68d3170b974",
            "type": "leaf",
            "state": {
              "type": "empty",
              "state": {},
              "icon": "lucide-file",
              "title": "新标签页"
            }
          }
        ]
      }
    ],
    "direction": "vertical"
  },
  "left": {
    "id": "1e52615e73d37b22",
    "type": "split",
    "children": [
      {
        "id": "383db4825bc7d644",
        "type": "tabs",
        "children": [
          {
            "id": "5ff3936d6105ec76",
            "type": "leaf",
            "state": {
              "type": "file-explorer",
              "state": {
                "sortOrder": "alphabetical",
                "autoReveal": false
              },
              "icon": "lucide-folder-closed",
              "title": "文件列表"
            }
          },
          {
            "id": "3b9db9aaa7766156",
            "type": "leaf",
            "state": {
              "type": "search",
              "state": {
                "query": "",
                "matchingCase": false,
                "explainSearch": false,
                "collapseAll": false,
                "extraContext": false,
                "sortOrder": "alphabetical"
              },
              "icon": "lucide-search",
              "title": "搜索"
            }
          },
          {
            "id": "8e234ab78adf0d9d",
            "type": "leaf",
            "state": {
              "type": "bookmarks",
              "state": {},
              "icon": "lucide-bookmark",
              "title": "书签"
            }
          }
        ]
      }
    ],
    "direction": "horizontal",
    "width": 300
  },
  "right": {
    "id": "e67d2e661bd62ac6",
    "type": "split",
    "children": [
      {
        "id": "25871255a461b08c",
        "type": "tabs",
        "children": [
          {
            "id": "688ba8dca48024f3",
            "type": "leaf",
            "state": {
              "type": "backlink",
              "state": {
                "collapseAll": false,
                "extraContext": false,
                "sortOrder": "alphabetical",
                "showSearch": false,
                "searchQuery": "",
                "backlinkCollapsed": false,
                "unlinkedCollapsed": true
              },
              "icon": "links-coming-in",
              "title": "反向链接"
            }
          },
          {
            "id": "d6c8d1d2e3a4ad1b",
            "type": "leaf",
            "state": {
              "type": "outgoing-link",
              "state": {
                "linksCollapsed": false,
                "unlinkedCollapsed": true
              },
              "icon": "links-going-out",
              "title": "出链"
            }
          },
          {
            "id": "11e198b37285a2ea",
            "type": "leaf",
            "state": {
              "type": "tag",
              "state": {
                "sortOrder": "frequency",
                "useHierarchy": true,
                "showSearch": false,
                "searchQuery": ""
              },
              "icon": "lucide-tags",
              "title": "标签"
            }
          },
          {
            "id": "6db2ab71ac4a60e7",
            "type": "leaf",
            "state": {
              "type": "outline",
              "state": {
                "followCursor": false,
                "showSearch": false,
                "searchQuery": ""
              },
              "icon": "lucide-list",
              "title": "大纲"
            }
          }
        ]
      }
    ],
    "direction": "horizontal",
    "width": 300,
    "collapsed": true
  },
  "left-ribbon": {
    "hiddenItems": {
      "switcher:打开快速切换": false,
      "graph:查看关系图谱": false,
      "canvas:新建白板": false,
      "daily-notes:打开/创建今天的日记": false,
      "templates:插入模板": false,
      "command-palette:打开命令面板": false
    }
  },
  "active": "f659e68d3170b974",
  "lastOpenFiles": [
    "README.md",
    "未命名.canvas"
  ]
}